README.md
setup.cfg
setup.py
drain3/__init__.py
drain3/drain.py
drain3/file_persistence.py
drain3/kafka_persistence.py
drain3/masking.py
drain3/memory_buffer_persistence.py
drain3/persistence_handler.py
drain3/redis_persistence.py
drain3/simple_profiler.py
drain3/template_miner.py
drain3/template_miner_config.py
drain3.egg-info/PKG-INFO
drain3.egg-info/SOURCES.txt
drain3.egg-info/dependency_links.txt
drain3.egg-info/requires.txt
drain3.egg-info/top_level.txt