Metadata-Version: 2.1
Name: drain3
Version: 0.9.3
Summary: Persistent & streaming log template miner
Home-page: https://github.com/IBM/Drain3
Author: IBM Research Haifa
Author-email: david.ohana@ibm.com
License: MIT
Download-URL: https://github.com/IBM/Drain3/archive/v_01.tar.gz
Keywords: drain,log,parser,IBM,template,logs,miner
Platform: UNKNOWN
Classifier: Programming Language :: Python :: 3.6
Classifier: Programming Language :: Python :: 3.7
Classifier: License :: OSI Approved :: MIT License
Classifier: Operating System :: OS Independent
Classifier: Topic :: Software Development :: Libraries
Provides-Extra: kafka
Provides-Extra: redis
